pyautotype/__init__.py
pyautotype/__main__.py
pyautotype/pyautotype.py
pyautotype-0.1.2.dist-info/METADATA
pyautotype-0.1.2.dist-info/WHEEL
pyautotype-0.1.2.dist-info/entry_points.txt
pyautotype-0.1.2.dist-info/top_level.txt
pyautotype-0.1.2.dist-info/RECORD
